smartmetertx/README.md
smartmetertx/__init__.py
smartmetertx/_version.py
smartmetertx/api.py
smartmetertx/controller.py
smartmetertx/meterReport.py
smartmetertx/notify.py
smartmetertx/server.py
smartmetertx/smtx2mongo.py
smartmetertx/utils.py
smartmetertx2mongo-1.3.0.data/data/share/smartmetertx/index.css
smartmetertx2mongo-1.3.0.data/data/share/smartmetertx/index.html
smartmetertx2mongo-1.3.0.data/data/share/smartmetertx/index.js
smartmetertx2mongo-1.3.0.dist-info/licenses/AUTHORS
smartmetertx2mongo-1.3.0.dist-info/licenses/COPYING
smartmetertx2mongo-1.3.0.dist-info/licenses/LICENSE
smartmetertx2mongo-1.3.0.dist-info/licenses/NOTICE
ui/index.css
ui/index.html
ui/index.js
smartmetertx2mongo-1.3.0.dist-info/METADATA
smartmetertx2mongo-1.3.0.dist-info/WHEEL
smartmetertx2mongo-1.3.0.dist-info/entry_points.txt
smartmetertx2mongo-1.3.0.dist-info/top_level.txt
smartmetertx2mongo-1.3.0.dist-info/RECORD
