Metadata-Version: 2.4
Name: smartmetertx2mongo
Version: 1.3.0
Summary: Implementation of SmartMeter Texas to store reads in MongoDB and serve a simple UI/API.
Author-email: Markizano Draconus <markizano@markizano.net>
License-Expression: GPL-3.0-or-later
Project-URL: Homepage, https://markizano.net
Project-URL: Repository, https://github.com/markizano/smartmetertx
Project-URL: Issues, https://github.com/markizano/smartmetertx/issues
Project-URL: Documentation, https://docs.markizano.net
Requires-Python: >=3.9
License-File: LICENSE
License-File: COPYING
License-File: NOTICE
License-File: AUTHORS
Requires-Dist: CherryPy==18.10.0
Requires-Dist: Jinja2==3.1.6
Requires-Dist: PyYAML==6.0.2
Requires-Dist: boto3==1.40.28
Requires-Dist: dateparser==1.2.2
Requires-Dist: kizano==1.0.6
Requires-Dist: pymongo==4.15.0
Requires-Dist: python-gnupg==0.5.5
Requires-Dist: requests==2.32.5
Dynamic: license-file
